odoo/addons/commission_delegated_partner/README.rst
odoo/addons/commission_delegated_partner/__init__.py
odoo/addons/commission_delegated_partner/__manifest__.py
odoo/addons/commission_delegated_partner/i18n/commission_delegated_partner.pot
odoo/addons/commission_delegated_partner/i18n/es.po
odoo/addons/commission_delegated_partner/i18n/it.po
odoo/addons/commission_delegated_partner/i18n/pt.po
odoo/addons/commission_delegated_partner/i18n/pt_BR.po
odoo/addons/commission_delegated_partner/i18n/sale_commission_delegated_partner.pot
odoo/addons/commission_delegated_partner/models/__init__.py
odoo/addons/commission_delegated_partner/models/commission_settlement.py
odoo/addons/commission_delegated_partner/models/res_partner.py
odoo/addons/commission_delegated_partner/readme/CONFIGURE.rst
odoo/addons/commission_delegated_partner/readme/CONTRIBUTORS.rst
odoo/addons/commission_delegated_partner/readme/DESCRIPTION.rst
odoo/addons/commission_delegated_partner/static/description/icon.png
odoo/addons/commission_delegated_partner/static/description/index.html
odoo/addons/commission_delegated_partner/tests/__init__.py
odoo/addons/commission_delegated_partner/tests/test_commission_delegate_partner.py
odoo/addons/commission_delegated_partner/views/res_partner.xml
odoo_addon_commission_delegated_partner-16.0.1.0.1.2.dist-info/METADATA
odoo_addon_commission_delegated_partner-16.0.1.0.1.2.dist-info/WHEEL
odoo_addon_commission_delegated_partner-16.0.1.0.1.2.dist-info/top_level.txt
odoo_addon_commission_delegated_partner-16.0.1.0.1.2.dist-info/RECORD
