Metadata-Version: 2.1
Name: odoo-addon-commission_delegated_partner
Version: 16.0.1.0.1.2
Summary: Allow to delegate the invoices of agent to a delegate partner
Home-page: https://github.com/OCA/commission
Author: Creu Blanca,Odoo Community Association (OCA)
Author-email: support@odoo-community.org
License: AGPL-3
Classifier: Programming Language :: Python
Classifier: Framework :: Odoo
Classifier: Framework :: Odoo :: 16.0
Classifier: License :: OSI Approved :: GNU Affero General Public License v3
Requires-Python: >=3.10
Requires-Dist: odoo-addon-account-commission<16.1dev,>=16.0dev
Requires-Dist: odoo<16.1dev,>=16.0a
